setup.py
tests/__init__.py
tests/test_report.py
trackyou/__init__.py
trackyou/trackyou.py
trackyou.egg-info/PKG-INFO
trackyou.egg-info/SOURCES.txt
trackyou.egg-info/dependency_links.txt
trackyou.egg-info/top_level.txt
trackyou/modules/__init__.py
trackyou/modules/plotter.py