Metadata-Version: 1.0
Name: trackyou
Version: 0.0.2
Summary: visualize your progress
Home-page: https://github.com/himkt/trackyou
Author: himkt
Author-email: himkt@klis.tsukuba.ac.jp
License: UNKNOWN
Platform: UNKNOWN
